rate_limiters/__init__.py
rate_limiters/rate_limiters.py
rate_limiters/rates.py
rate_limiters-0.2.10.dist-info/METADATA
rate_limiters-0.2.10.dist-info/WHEEL
rate_limiters-0.2.10.dist-info/top_level.txt
rate_limiters-0.2.10.dist-info/RECORD
