Metadata-Version: 2.1
Name: rate-limiters
Version: 0.2.10
Summary: Rate limiters for APIs and web scraping.
Requires-Dist: quicklogs
Provides-Extra: dev
Requires-Dist: black ; extra == 'dev'
Requires-Dist: pytest ; extra == 'dev'
Requires-Dist: pytest-asyncio ; extra == 'dev'
